{
  "id": 3955812173,
  "id_str": "3955812173",
  "name": "Эброд Андерхуд",
  "screen_name": "abroadunderhood",
  "location": "Лиссабон, Португалия",
  "profile_location": null,
  "description": "Авторка недели Аня из Берлина (работаю удаленно из Лиссабона). Канал в Телеграме: https://t.co/AcRfR8wlDE",
  "url": "https://t.co/KN9hDb6yA6",
  "entities": {
    "url": {
      "urls": [
        {
          "url": "https://t.co/KN9hDb6yA6",
          "expanded_url": "https://abroadunderhood.ru",
          "display_url": "abroadunderhood.ru",
          "indices": [
            0,
            23
          ]
        }
      ]
    },
    "description": {
      "urls": [
        {
          "url": "https://t.co/AcRfR8wlDE",
          "expanded_url": "http://t.me/isvidanka",
          "display_url": "t.me/isvidanka",
          "indices": [
            82,
            105
          ]
        }
      ]
    }
  },
  "protected": false,
  "followers_count": 31859,
  "friends_count": 0,
  "listed_count": 314,
  "created_at": "Wed Oct 14 12:33:52 +0000 2015",
  "favourites_count": 31639,
  "utc_offset": null,
  "time_zone": null,
  "geo_enabled": true,
  "verified": false,
  "statuses_count": 147649,
  "lang": null,
  "status": {
    "created_at": "Sun Sep 06 19:36:00 +0000 2020",
    "id": 1302692044142506000,
    "id_str": "1302692044142505984",
    "text": "Если у вас остались вопросы, можно писать мне в личку, постараюсь ответить на самое важное.",
    "truncated": false,
    "entities": {
      "hashtags": [],
      "symbols": [],
      "user_mentions": [],
      "urls": []
    },
    "source": "<a href=\"https://mobile.twitter.com\" rel=\"nofollow\">Twitter Web App</a>",
    "in_reply_to_status_id": 1302692042766725000,
    "in_reply_to_status_id_str": "1302692042766725132",
    "in_reply_to_user_id": 3955812173,
    "in_reply_to_user_id_str": "3955812173",
    "in_reply_to_screen_name": "abroadunderhood",
    "geo": null,
    "coordinates": null,
    "place": null,
    "contributors": null,
    "is_quote_status": false,
    "retweet_count": 0,
    "favorite_count": 13,
    "favorited": false,
    "retweeted": false,
    "lang": "ru"
  },
  "contributors_enabled": false,
  "is_translator": false,
  "is_translation_enabled": false,
  "profile_background_color": "000000",
  "profile_background_image_url": "http://abs.twimg.com/images/themes/theme1/bg.png",
  "profile_background_image_url_https": "https://abs.twimg.com/images/themes/theme1/bg.png",
  "profile_background_tile": false,
  "profile_image_url": "http://pbs.twimg.com/profile_images/1300389030174040064/u5D3YLcj_normal.jpg",
  "profile_image_url_https": "https://pbs.twimg.com/profile_images/1300389030174040064/u5D3YLcj_normal.jpg",
  "profile_banner_url": "https://pbs.twimg.com/profile_banners/3955812173/1598871882",
  "profile_link_color": "1B95E0",
  "profile_sidebar_border_color": "000000",
  "profile_sidebar_fill_color": "000000",
  "profile_text_color": "000000",
  "profile_use_background_image": false,
  "has_extended_profile": false,
  "default_profile": false,
  "default_profile_image": false,
  "following": false,
  "follow_request_sent": false,
  "notifications": false,
  "translator_type": "none",
  "suspended": false,
  "needs_phone_verification": false,
  "time_zone_offset": 0,
  "geometry": {
    "lat": 0,
    "lng": 0
  }
}
