{
  "mentions": [
    {
      "created_at": "Mon Dec 24 10:08:48 +0000 2018",
      "id": 1077144048178221000,
      "id_str": "1077144048178221058",
      "text": "@abroadunderhood @olgazju Дождались! Ура!",
      "truncated": false,
      "entities": {
        "hashtags": [],
        "symbols": [],
        "user_mentions": [
          {
            "screen_name": "abroadunderhood",
            "name": "Эброд Андерхуд",
            "id": 3955812173,
            "id_str": "3955812173",
            "indices": [
              0,
              16
            ]
          },
          {
            "screen_name": "olgazju",
            "name": "OlgaZju",
            "id": 229657175,
            "id_str": "229657175",
            "indices": [
              17,
              25
            ]
          }
        ],
        "urls": []
      },
      "source": "<a href=\"http://twitter.com/download/iphone\" rel=\"nofollow\">Twitter for iPhone</a>",
      "in_reply_to_status_id": 1077143921321525200,
      "in_reply_to_status_id_str": "1077143921321525249",
      "in_reply_to_user_id": 3955812173,
      "in_reply_to_user_id_str": "3955812173",
      "in_reply_to_screen_name": "abroadunderhood",
      "user": {
        "id": 123356858,
        "id_str": "123356858"
      },
      "geo": null,
      "coordinates": null,
      "place": null,
      "contributors": null,
      "is_quote_status": false,
      "retweet_count": 0,
      "favorite_count": 0,
      "favorited": false,
      "retweeted": false,
      "lang": "ru"
    },
    {
      "created_at": "Mon Dec 24 10:09:35 +0000 2018",
      "id": 1077144246078062600,
      "id_str": "1077144246078062592",
      "text": "@abroadunderhood @olgazju Оооо!!! Шалом!! Любимый Израиль!!! Обожаю эту страну!! Жду с нетерпением!! Удачной недели!!!",
      "truncated": false,
      "entities": {
        "hashtags": [],
        "symbols": [],
        "user_mentions": [
          {
            "screen_name": "abroadunderhood",
            "name": "Эброд Андерхуд",
            "id": 3955812173,
            "id_str": "3955812173",
            "indices": [
              0,
              16
            ]
          },
          {
            "screen_name": "olgazju",
            "name": "OlgaZju",
            "id": 229657175,
            "id_str": "229657175",
            "indices": [
              17,
              25
            ]
          }
        ],
        "urls": []
      },
      "source": "<a href=\"https://about.twitter.com/products/tweetdeck\" rel=\"nofollow\">TweetDeck</a>",
      "in_reply_to_status_id": 1077143921321525200,
      "in_reply_to_status_id_str": "1077143921321525249",
      "in_reply_to_user_id": 3955812173,
      "in_reply_to_user_id_str": "3955812173",
      "in_reply_to_screen_name": "abroadunderhood",
      "user": {
        "id": 211214492,
        "id_str": "211214492"
      },
      "geo": null,
      "coordinates": null,
      "place": null,
      "contributors": null,
      "is_quote_status": false,
      "retweet_count": 0,
      "favorite_count": 0,
      "favorited": false,
      "retweeted": false,
      "lang": "ru"
    },
    {
      "created_at": "Mon Dec 24 10:10:03 +0000 2018",
      "id": 1077144363946389500,
      "id_str": "1077144363946389505",
      "text": "@abroadunderhood @olgazju /cc @Romka_Gold",
      "truncated": false,
      "entities": {
        "hashtags": [],
        "symbols": [],
        "user_mentions": [
          {
            "screen_name": "abroadunderhood",
            "name": "Эброд Андерхуд",
            "id": 3955812173,
            "id_str": "3955812173",
            "indices": [
              0,
              16
            ]
          },
          {
            "screen_name": "olgazju",
            "name": "OlgaZju",
            "id": 229657175,
            "id_str": "229657175",
            "indices": [
              17,
              25
            ]
          },
          {
            "screen_name": "Romka_Gold",
            "name": "Хуцпа и Савланут",
            "id": 165204725,
            "id_str": "165204725",
            "indices": [
              30,
              41
            ]
          }
        ],
        "urls": []
      },
      "source": "<a href=\"http://twitter.com\" rel=\"nofollow\">Twitter Web Client</a>",
      "in_reply_to_status_id": 1077143921321525200,
      "in_reply_to_status_id_str": "1077143921321525249",
      "in_reply_to_user_id": 3955812173,
      "in_reply_to_user_id_str": "3955812173",
      "in_reply_to_screen_name": "abroadunderhood",
      "user": {
        "id": 1491081,
        "id_str": "1491081"
      },
      "geo": null,
      "coordinates": null,
      "place": null,
      "contributors": null,
      "is_quote_status": false,
      "retweet_count": 0,
      "favorite_count": 0,
      "favorited": false,
      "retweeted": false,
      "lang": "und"
    },
    {
      "created_at": "Mon Dec 24 10:10:20 +0000 2018",
      "id": 1077144434788184000,
      "id_str": "1077144434788184064",
      "text": "@abroadunderhood @olgazju שלומ!",
      "truncated": false,
      "entities": {
        "hashtags": [],
        "symbols": [],
        "user_mentions": [
          {
            "screen_name": "abroadunderhood",
            "name": "Эброд Андерхуд",
            "id": 3955812173,
            "id_str": "3955812173",
            "indices": [
              0,
              16
            ]
          },
          {
            "screen_name": "olgazju",
            "name": "OlgaZju",
            "id": 229657175,
            "id_str": "229657175",
            "indices": [
              17,
              25
            ]
          }
        ],
        "urls": []
      },
      "source": "<a href=\"http://twitter.com/download/android\" rel=\"nofollow\">Twitter for Android</a>",
      "in_reply_to_status_id": 1077143921321525200,
      "in_reply_to_status_id_str": "1077143921321525249",
      "in_reply_to_user_id": 3955812173,
      "in_reply_to_user_id_str": "3955812173",
      "in_reply_to_screen_name": "abroadunderhood",
      "user": {
        "id": 168052210,
        "id_str": "168052210"
      },
      "geo": null,
      "coordinates": null,
      "place": null,
      "contributors": null,
      "is_quote_status": false,
      "retweet_count": 0,
      "favorite_count": 0,
      "favorited": false,
      "retweeted": false,
      "lang": "iw"
    },
    {
      "created_at": "Mon Dec 24 10:10:41 +0000 2018",
      "id": 1077144525540335600,
      "id_str": "1077144525540335622",
      "text": "@abroadunderhood @olgazju шаббат акбр!",
      "truncated": false,
      "entities": {
        "hashtags": [],
        "symbols": [],
        "user_mentions": [
          {
            "screen_name": "abroadunderhood",
            "name": "Эброд Андерхуд",
            "id": 3955812173,
            "id_str": "3955812173",
            "indices": [
              0,
              16
            ]
          },
          {
            "screen_name": "olgazju",
            "name": "OlgaZju",
            "id": 229657175,
            "id_str": "229657175",
            "indices": [
              17,
              25
            ]
          }
        ],
        "urls": []
      },
      "source": "<a href=\"http://twitter.com/download/android\" rel=\"nofollow\">Twitter for Android</a>",
      "in_reply_to_status_id": 1077143921321525200,
      "in_reply_to_status_id_str": "1077143921321525249",
      "in_reply_to_user_id": 3955812173,
      "in_reply_to_user_id_str": "3955812173",
      "in_reply_to_screen_name": "abroadunderhood",
      "user": {
        "id": 210636758,
        "id_str": "210636758"
      },
      "geo": null,
      "coordinates": null,
      "place": null,
      "contributors": null,
      "is_quote_status": false,
      "retweet_count": 0,
      "favorite_count": 0,
      "favorited": false,
      "retweeted": false,
      "lang": "bg"
    },
    {
      "created_at": "Mon Dec 24 10:11:11 +0000 2018",
      "id": 1077144648194375700,
      "id_str": "1077144648194375680",
      "text": "@abroadunderhood @olgazju АХАХАХАХА ПРИВЕТ",
      "truncated": false,
      "entities": {
        "hashtags": [],
        "symbols": [],
        "user_mentions": [
          {
            "screen_name": "abroadunderhood",
            "name": "Эброд Андерхуд",
            "id": 3955812173,
            "id_str": "3955812173",
            "indices": [
              0,
              16
            ]
          },
          {
            "screen_name": "olgazju",
            "name": "OlgaZju",
            "id": 229657175,
            "id_str": "229657175",
            "indices": [
              17,
              25
            ]
          }
        ],
        "urls": []
      },
      "source": "<a href=\"http://tapbots.com/tweetbot\" rel=\"nofollow\">Tweetbot for iΟS</a>",
      "in_reply_to_status_id": 1077143921321525200,
      "in_reply_to_status_id_str": "1077143921321525249",
      "in_reply_to_user_id": 3955812173,
      "in_reply_to_user_id_str": "3955812173",
      "in_reply_to_screen_name": "abroadunderhood",
      "user": {
        "id": 165204725,
        "id_str": "165204725"
      },
      "geo": null,
      "coordinates": null,
      "place": {
        "id": "2edb6e240797c549",
        "url": "https://api.twitter.com/1.1/geo/id/2edb6e240797c549.json",
        "place_type": "country",
        "name": "Israel",
        "full_name": "Israel",
        "country_code": "IL",
        "country": "Israel",
        "contained_within": [],
        "bounding_box": {
          "type": "Polygon",
          "coordinates": [
            [
              [
                34.266924,
                29.393973
              ],
              [
                35.669933,
                29.393973
              ],
              [
                35.669933,
                33.290533
              ],
              [
                34.266924,
                33.290533
              ]
            ]
          ]
        },
        "attributes": {}
      },
      "contributors": null,
      "is_quote_status": false,
      "retweet_count": 0,
      "favorite_count": 1,
      "favorited": false,
      "retweeted": false,
      "lang": "ru"
    },
    {
      "created_at": "Mon Dec 24 10:11:38 +0000 2018",
      "id": 1077144762573037600,
      "id_str": "1077144762573037568",
      "text": "@abroadunderhood @olgazju супер, давай все самое интересное и спорт зацепи",
      "truncated": false,
      "entities": {
        "hashtags": [],
        "symbols": [],
        "user_mentions": [
          {
            "screen_name": "abroadunderhood",
            "name": "Эброд Андерхуд",
            "id": 3955812173,
            "id_str": "3955812173",
            "indices": [
              0,
              16
            ]
          },
          {
            "screen_name": "olgazju",
            "name": "OlgaZju",
            "id": 229657175,
            "id_str": "229657175",
            "indices": [
              17,
              25
            ]
          }
        ],
        "urls": []
      },
      "source": "<a href=\"http://twitter.com\" rel=\"nofollow\">Twitter Web Client</a>",
      "in_reply_to_status_id": 1077143921321525200,
      "in_reply_to_status_id_str": "1077143921321525249",
      "in_reply_to_user_id": 3955812173,
      "in_reply_to_user_id_str": "3955812173",
      "in_reply_to_screen_name": "abroadunderhood",
      "user": {
        "id": 2777935424,
        "id_str": "2777935424"
      },
      "geo": null,
      "coordinates": null,
      "place": null,
      "contributors": null,
      "is_quote_status": false,
      "retweet_count": 0,
      "favorite_count": 0,
      "favorited": false,
      "retweeted": false,
      "lang": "ru"
    },
    {
      "created_at": "Mon Dec 24 10:11:38 +0000 2018",
      "id": 1077144762615062500,
      "id_str": "1077144762615062535",
      "text": "тель-авивский @abroadunderhood ! :)",
      "truncated": false,
      "entities": {
        "hashtags": [],
        "symbols": [],
        "user_mentions": [
          {
            "screen_name": "abroadunderhood",
            "name": "Эброд Андерхуд",
            "id": 3955812173,
            "id_str": "3955812173",
            "indices": [
              14,
              30
            ]
          }
        ],
        "urls": []
      },
      "source": "<a href=\"https://tapbots.com/software/tweetbot/mac\" rel=\"nofollow\">Tweetbot for Mac</a>",
      "in_reply_to_status_id": null,
      "in_reply_to_status_id_str": null,
      "in_reply_to_user_id": null,
      "in_reply_to_user_id_str": null,
      "in_reply_to_screen_name": null,
      "user": {
        "id": 22622747,
        "id_str": "22622747"
      },
      "geo": null,
      "coordinates": null,
      "place": null,
      "contributors": null,
      "is_quote_status": false,
      "retweet_count": 0,
      "favorite_count": 0,
      "favorited": false,
      "retweeted": false,
      "lang": "uk"
    },
    {
      "created_at": "Mon Dec 24 10:12:17 +0000 2018",
      "id": 1077144925546913800,
      "id_str": "1077144925546913792",
      "text": "@abroadunderhood Тогда рассказывайте, как выйти замуж за еврея и где его встретить)",
      "truncated": false,
      "entities": {
        "hashtags": [],
        "symbols": [],
        "user_mentions": [
          {
            "screen_name": "abroadunderhood",
            "name": "Эброд Андерхуд",
            "id": 3955812173,
            "id_str": "3955812173",
            "indices": [
              0,
              16
            ]
          }
        ],
        "urls": []
      },
      "source": "<a href=\"http://twitter.com/download/android\" rel=\"nofollow\">Twitter for Android</a>",
      "in_reply_to_status_id": 1077144409056165900,
      "in_reply_to_status_id_str": "1077144409056165888",
      "in_reply_to_user_id": 3955812173,
      "in_reply_to_user_id_str": "3955812173",
      "in_reply_to_screen_name": "abroadunderhood",
      "user": {
        "id": 168052210,
        "id_str": "168052210"
      },
      "geo": null,
      "coordinates": null,
      "place": null,
      "contributors": null,
      "is_quote_status": false,
      "retweet_count": 0,
      "favorite_count": 1,
      "favorited": false,
      "retweeted": false,
      "lang": "ru"
    },
    {
      "created_at": "Mon Dec 24 10:12:18 +0000 2018",
      "id": 1077144929959403500,
      "id_str": "1077144929959403520",
      "text": "@abroadunderhood @olgazju Опять?)))",
      "truncated": false,
      "entities": {
        "hashtags": [],
        "symbols": [],
        "user_mentions": [
          {
            "screen_name": "abroadunderhood",
            "name": "Эброд Андерхуд",
            "id": 3955812173,
            "id_str": "3955812173",
            "indices": [
              0,
              16
            ]
          },
          {
            "screen_name": "olgazju",
            "name": "OlgaZju",
            "id": 229657175,
            "id_str": "229657175",
            "indices": [
              17,
              25
            ]
          }
        ],
        "urls": []
      },
      "source": "<a href=\"http://twitter.com/download/iphone\" rel=\"nofollow\">Twitter for iPhone</a>",
      "in_reply_to_status_id": 1077143921321525200,
      "in_reply_to_status_id_str": "1077143921321525249",
      "in_reply_to_user_id": 3955812173,
      "in_reply_to_user_id_str": "3955812173",
      "in_reply_to_screen_name": "abroadunderhood",
      "user": {
        "id": 20824799,
        "id_str": "20824799"
      },
      "geo": null,
      "coordinates": null,
      "place": null,
      "contributors": null,
      "is_quote_status": false,
      "retweet_count": 0,
      "favorite_count": 0,
      "favorited": false,
      "retweeted": false,
      "lang": "ru"
    },
    {
      "created_at": "Mon Dec 24 10:12:24 +0000 2018",
      "id": 1077144955053883400,
      "id_str": "1077144955053883392",
      "text": "@abroadunderhood @olgazju )",
      "truncated": false,
      "entities": {
        "hashtags": [],
        "symbols": [],
        "user_mentions": [
          {
            "screen_name": "abroadunderhood",
            "name": "Эброд Андерхуд",
            "id": 3955812173,
            "id_str": "3955812173",
            "indices": [
              0,
              16
            ]
          },
          {
            "screen_name": "olgazju",
            "name": "OlgaZju",
            "id": 229657175,
            "id_str": "229657175",
            "indices": [
              17,
              25
            ]
          }
        ],
        "urls": []
      },
      "source": "<a href=\"http://twitter.com/download/android\" rel=\"nofollow\">Twitter for Android</a>",
      "in_reply_to_status_id": 1077143921321525200,
      "in_reply_to_status_id_str": "1077143921321525249",
      "in_reply_to_user_id": 3955812173,
      "in_reply_to_user_id_str": "3955812173",
      "in_reply_to_screen_name": "abroadunderhood",
      "user": {
        "id": 2288885673,
        "id_str": "2288885673"
      },
      "geo": null,
      "coordinates": null,
      "place": null,
      "contributors": null,
      "is_quote_status": false,
      "retweet_count": 0,
      "favorite_count": 0,
      "favorited": false,
      "retweeted": false,
      "lang": "und"
    },
    {
      "created_at": "Mon Dec 24 10:12:52 +0000 2018",
      "id": 1077145075048738800,
      "id_str": "1077145075048738817",
      "text": "@abroadunderhood ну вот... никакой интриги - сразу все секреты раскрыла",
      "truncated": false,
      "entities": {
        "hashtags": [],
        "symbols": [],
        "user_mentions": [
          {
            "screen_name": "abroadunderhood",
            "name": "Эброд Андерхуд",
            "id": 3955812173,
            "id_str": "3955812173",
            "indices": [
              0,
              16
            ]
          }
        ],
        "urls": []
      },
      "source": "<a href=\"http://twitter.com/download/android\" rel=\"nofollow\">Twitter for Android</a>",
      "in_reply_to_status_id": 1077144409056165900,
      "in_reply_to_status_id_str": "1077144409056165888",
      "in_reply_to_user_id": 3955812173,
      "in_reply_to_user_id_str": "3955812173",
      "in_reply_to_screen_name": "abroadunderhood",
      "user": {
        "id": 210636758,
        "id_str": "210636758"
      },
      "geo": null,
      "coordinates": null,
      "place": null,
      "contributors": null,
      "is_quote_status": false,
      "retweet_count": 0,
      "favorite_count": 1,
      "favorited": false,
      "retweeted": false,
      "lang": "ru"
    },
    {
      "created_at": "Mon Dec 24 10:12:58 +0000 2018",
      "id": 1077145098532606000,
      "id_str": "1077145098532605957",
      "text": "@abroadunderhood @olgazju Шалом! Второй Израиль!",
      "truncated": false,
      "entities": {
        "hashtags": [],
        "symbols": [],
        "user_mentions": [
          {
            "screen_name": "abroadunderhood",
            "name": "Эброд Андерхуд",
            "id": 3955812173,
            "id_str": "3955812173",
            "indices": [
              0,
              16
            ]
          },
          {
            "screen_name": "olgazju",
            "name": "OlgaZju",
            "id": 229657175,
            "id_str": "229657175",
            "indices": [
              17,
              25
            ]
          }
        ],
        "urls": []
      },
      "source": "<a href=\"http://mvilla.it/fenix\" rel=\"nofollow\">Fenix 2</a>",
      "in_reply_to_status_id": 1077143921321525200,
      "in_reply_to_status_id_str": "1077143921321525249",
      "in_reply_to_user_id": 3955812173,
      "in_reply_to_user_id_str": "3955812173",
      "in_reply_to_screen_name": "abroadunderhood",
      "user": {
        "id": 169993781,
        "id_str": "169993781"
      },
      "geo": null,
      "coordinates": null,
      "place": null,
      "contributors": null,
      "is_quote_status": false,
      "retweet_count": 0,
      "favorite_count": 1,
      "favorited": true,
      "retweeted": false,
      "lang": "ru"
    },
    {
      "created_at": "Mon Dec 24 10:12:58 +0000 2018",
      "id": 1077145098985635800,
      "id_str": "1077145098985635842",
      "text": "@abroadunderhood @olgazju Шалом! Наконец то родная иудея!! Как знал прям;)",
      "truncated": false,
      "entities": {
        "hashtags": [],
        "symbols": [],
        "user_mentions": [
          {
            "screen_name": "abroadunderhood",
            "name": "Эброд Андерхуд",
            "id": 3955812173,
            "id_str": "3955812173",
            "indices": [
              0,
              16
            ]
          },
          {
            "screen_name": "olgazju",
            "name": "OlgaZju",
            "id": 229657175,
            "id_str": "229657175",
            "indices": [
              17,
              25
            ]
          }
        ],
        "urls": []
      },
      "source": "<a href=\"http://tapbots.com/tweetbot\" rel=\"nofollow\">Tweetbot for iΟS</a>",
      "in_reply_to_status_id": 1077143921321525200,
      "in_reply_to_status_id_str": "1077143921321525249",
      "in_reply_to_user_id": 3955812173,
      "in_reply_to_user_id_str": "3955812173",
      "in_reply_to_screen_name": "abroadunderhood",
      "user": {
        "id": 22441561,
        "id_str": "22441561"
      },
      "geo": null,
      "coordinates": null,
      "place": {
        "id": "ed484e8043005985",
        "url": "https://api.twitter.com/1.1/geo/id/ed484e8043005985.json",
        "place_type": "city",
        "name": "Красное Село",
        "full_name": "Красное Село, Россия",
        "country_code": "RU",
        "country": "Russia",
        "contained_within": [],
        "bounding_box": {
          "type": "Polygon",
          "coordinates": [
            [
              [
                30.0347284,
                59.6918497
              ],
              [
                30.1601297,
                59.6918497
              ],
              [
                30.1601297,
                59.8090168
              ],
              [
                30.0347284,
                59.8090168
              ]
            ]
          ]
        },
        "attributes": {}
      },
      "contributors": null,
      "is_quote_status": false,
      "retweet_count": 0,
      "favorite_count": 1,
      "favorited": true,
      "retweeted": false,
      "lang": "ru"
    },
    {
      "created_at": "Mon Dec 24 10:13:51 +0000 2018",
      "id": 1077145321480835100,
      "id_str": "1077145321480835072",
      "text": "@abroadunderhood И Голани на фотках нам тоже..пустил скупую слезу;)",
      "truncated": false,
      "entities": {
        "hashtags": [],
        "symbols": [],
        "user_mentions": [
          {
            "screen_name": "abroadunderhood",
            "name": "Эброд Андерхуд",
            "id": 3955812173,
            "id_str": "3955812173",
            "indices": [
              0,
              16
            ]
          }
        ],
        "urls": []
      },
      "source": "<a href=\"http://tapbots.com/tweetbot\" rel=\"nofollow\">Tweetbot for iΟS</a>",
      "in_reply_to_status_id": 1077145072674721800,
      "in_reply_to_status_id_str": "1077145072674721794",
      "in_reply_to_user_id": 3955812173,
      "in_reply_to_user_id_str": "3955812173",
      "in_reply_to_screen_name": "abroadunderhood",
      "user": {
        "id": 22441561,
        "id_str": "22441561"
      },
      "geo": null,
      "coordinates": null,
      "place": {
        "id": "ed484e8043005985",
        "url": "https://api.twitter.com/1.1/geo/id/ed484e8043005985.json",
        "place_type": "city",
        "name": "Красное Село",
        "full_name": "Красное Село, Россия",
        "country_code": "RU",
        "country": "Russia",
        "contained_within": [],
        "bounding_box": {
          "type": "Polygon",
          "coordinates": [
            [
              [
                30.0347284,
                59.6918497
              ],
              [
                30.1601297,
                59.6918497
              ],
              [
                30.1601297,
                59.8090168
              ],
              [
                30.0347284,
                59.8090168
              ]
            ]
          ]
        },
        "attributes": {}
      },
      "contributors": null,
      "is_quote_status": false,
      "retweet_count": 0,
      "favorite_count": 0,
      "favorited": false,
      "retweeted": false,
      "lang": "ru"
    },
    {
      "created_at": "Mon Dec 24 10:13:59 +0000 2018",
      "id": 1077145353433026600,
      "id_str": "1077145353433026560",
      "text": "@abroadunderhood Зелёный снег...? 🤔🙄",
      "truncated": false,
      "entities": {
        "hashtags": [],
        "symbols": [],
        "user_mentions": [
          {
            "screen_name": "abroadunderhood",
            "name": "Эброд Андерхуд",
            "id": 3955812173,
            "id_str": "3955812173",
            "indices": [
              0,
              16
            ]
          }
        ],
        "urls": []
      },
      "source": "<a href=\"http://twitter.com/download/android\" rel=\"nofollow\">Twitter for Android</a>",
      "in_reply_to_status_id": 1077145072674721800,
      "in_reply_to_status_id_str": "1077145072674721794",
      "in_reply_to_user_id": 3955812173,
      "in_reply_to_user_id_str": "3955812173",
      "in_reply_to_screen_name": "abroadunderhood",
      "user": {
        "id": 2403116653,
        "id_str": "2403116653"
      },
      "geo": null,
      "coordinates": null,
      "place": null,
      "contributors": null,
      "is_quote_status": false,
      "retweet_count": 0,
      "favorite_count": 0,
      "favorited": false,
      "retweeted": false,
      "lang": "ru"
    },
    {
      "created_at": "Mon Dec 24 10:14:37 +0000 2018",
      "id": 1077145514234310700,
      "id_str": "1077145514234310656",
      "text": "@abroadunderhood Неделя обещает быть интересной ; ) Зайдём с козырей -- когда будет построен Третий Храм? )",
      "truncated": false,
      "entities": {
        "hashtags": [],
        "symbols": [],
        "user_mentions": [
          {
            "screen_name": "abroadunderhood",
            "name": "Эброд Андерхуд",
            "id": 3955812173,
            "id_str": "3955812173",
            "indices": [
              0,
              16
            ]
          }
        ],
        "urls": []
      },
      "source": "<a href=\"http://twitter.com\" rel=\"nofollow\">Twitter Web Client</a>",
      "in_reply_to_status_id": 1077144409056165900,
      "in_reply_to_status_id_str": "1077144409056165888",
      "in_reply_to_user_id": 3955812173,
      "in_reply_to_user_id_str": "3955812173",
      "in_reply_to_screen_name": "abroadunderhood",
      "user": {
        "id": 255899918,
        "id_str": "255899918"
      },
      "geo": null,
      "coordinates": null,
      "place": null,
      "contributors": null,
      "is_quote_status": false,
      "retweet_count": 0,
      "favorite_count": 0,
      "favorited": false,
      "retweeted": false,
      "lang": "ru"
    },
    {
      "created_at": "Mon Dec 24 10:15:32 +0000 2018",
      "id": 1077145745742950400,
      "id_str": "1077145745742950400",
      "text": "@abroadunderhood Еще бы... Пальмы скукожились",
      "truncated": false,
      "entities": {
        "hashtags": [],
        "symbols": [],
        "user_mentions": [
          {
            "screen_name": "abroadunderhood",
            "name": "Эброд Андерхуд",
            "id": 3955812173,
            "id_str": "3955812173",
            "indices": [
              0,
              16
            ]
          }
        ],
        "urls": []
      },
      "source": "<a href=\"http://twitter.com\" rel=\"nofollow\">Twitter Web Client</a>",
      "in_reply_to_status_id": 1077145072674721800,
      "in_reply_to_status_id_str": "1077145072674721794",
      "in_reply_to_user_id": 3955812173,
      "in_reply_to_user_id_str": "3955812173",
      "in_reply_to_screen_name": "abroadunderhood",
      "user": {
        "id": 2554906118,
        "id_str": "2554906118"
      },
      "geo": null,
      "coordinates": null,
      "place": null,
      "contributors": null,
      "is_quote_status": false,
      "retweet_count": 0,
      "favorite_count": 0,
      "favorited": false,
      "retweeted": false,
      "lang": "ru"
    },
    {
      "created_at": "Mon Dec 24 10:16:23 +0000 2018",
      "id": 1077145957769326600,
      "id_str": "1077145957769326592",
      "text": "@abroadunderhood Для меня шоком стал 23 февраля прошлого года, когда я приехал из мерзости слякоти -3-5 в +25 Галилеи!)))",
      "truncated": false,
      "entities": {
        "hashtags": [],
        "symbols": [],
        "user_mentions": [
          {
            "screen_name": "abroadunderhood",
            "name": "Эброд Андерхуд",
            "id": 3955812173,
            "id_str": "3955812173",
            "indices": [
              0,
              16
            ]
          }
        ],
        "urls": []
      },
      "source": "<a href=\"https://about.twitter.com/products/tweetdeck\" rel=\"nofollow\">TweetDeck</a>",
      "in_reply_to_status_id": 1077145072674721800,
      "in_reply_to_status_id_str": "1077145072674721794",
      "in_reply_to_user_id": 3955812173,
      "in_reply_to_user_id_str": "3955812173",
      "in_reply_to_screen_name": "abroadunderhood",
      "user": {
        "id": 211214492,
        "id_str": "211214492"
      },
      "geo": null,
      "coordinates": null,
      "place": null,
      "contributors": null,
      "is_quote_status": false,
      "retweet_count": 0,
      "favorite_count": 0,
      "favorited": false,
      "retweeted": false,
      "lang": "ru"
    },
    {
      "created_at": "Mon Dec 24 10:17:03 +0000 2018",
      "id": 1077146124878823400,
      "id_str": "1077146124878823424",
      "text": "@abroadunderhood Ждать ли нам твиттов в субботу?",
      "truncated": false,
      "entities": {
        "hashtags": [],
        "symbols": [],
        "user_mentions": [
          {
            "screen_name": "abroadunderhood",
            "name": "Эброд Андерхуд",
            "id": 3955812173,
            "id_str": "3955812173",
            "indices": [
              0,
              16
            ]
          }
        ],
        "urls": []
      },
      "source": "<a href=\"http://www.samruston.co.uk\" rel=\"nofollow\">Flamingo for Android</a>",
      "in_reply_to_status_id": 1077144129468067800,
      "in_reply_to_status_id_str": "1077144129468067842",
      "in_reply_to_user_id": 3955812173,
      "in_reply_to_user_id_str": "3955812173",
      "in_reply_to_screen_name": "abroadunderhood",
      "user": {
        "id": 13020892,
        "id_str": "13020892"
      },
      "geo": null,
      "coordinates": null,
      "place": null,
      "contributors": null,
      "is_quote_status": false,
      "retweet_count": 0,
      "favorite_count": 3,
      "favorited": false,
      "retweeted": false,
      "lang": "ru"
    },
    {
      "created_at": "Mon Dec 24 10:17:22 +0000 2018",
      "id": 1077146205992505300,
      "id_str": "1077146205992505344",
      "text": "@abroadunderhood @olgazju \"Шыряюсь 10 лет и мне норм... Бухаю по литру водки в день 10 лет и мне норм... Работаю 16… https://t.co/ZJTvk5wupY",
      "truncated": true,
      "entities": {
        "hashtags": [],
        "symbols": [],
        "user_mentions": [
          {
            "screen_name": "abroadunderhood",
            "name": "Эброд Андерхуд",
            "id": 3955812173,
            "id_str": "3955812173",
            "indices": [
              0,
              16
            ]
          },
          {
            "screen_name": "olgazju",
            "name": "OlgaZju",
            "id": 229657175,
            "id_str": "229657175",
            "indices": [
              17,
              25
            ]
          }
        ],
        "urls": [
          {
            "url": "https://t.co/ZJTvk5wupY",
            "expanded_url": "https://twitter.com/i/web/status/1077146205992505344",
            "display_url": "twitter.com/i/web/status/1…",
            "indices": [
              117,
              140
            ]
          }
        ]
      },
      "source": "<a href=\"http://twitter.com/download/android\" rel=\"nofollow\">Twitter for Android</a>",
      "in_reply_to_status_id": 1077143921321525200,
      "in_reply_to_status_id_str": "1077143921321525249",
      "in_reply_to_user_id": 3955812173,
      "in_reply_to_user_id_str": "3955812173",
      "in_reply_to_screen_name": "abroadunderhood",
      "user": {
        "id": 515277374,
        "id_str": "515277374"
      },
      "geo": null,
      "coordinates": null,
      "place": null,
      "contributors": null,
      "is_quote_status": false,
      "retweet_count": 0,
      "favorite_count": 0,
      "favorited": false,
      "retweeted": false,
      "lang": "ru"
    },
    {
      "created_at": "Mon Dec 24 10:18:11 +0000 2018",
      "id": 1077146411786006500,
      "id_str": "1077146411786006528",
      "text": "@abroadunderhood Это вот из того дня, Хайфа!)))) 23.02.2017))) https://t.co/XKCoJ2DEWn",
      "truncated": false,
      "entities": {
        "hashtags": [],
        "symbols": [],
        "user_mentions": [
          {
            "screen_name": "abroadunderhood",
            "name": "Эброд Андерхуд",
            "id": 3955812173,
            "id_str": "3955812173",
            "indices": [
              0,
              16
            ]
          }
        ],
        "urls": [],
        "media": [
          {
            "id": 1077146289660411900,
            "id_str": "1077146289660411905",
            "indices": [
              63,
              86
            ],
            "media_url": "http://pbs.twimg.com/media/DvLK1-5WwAEiwpm.jpg",
            "media_url_https": "https://pbs.twimg.com/media/DvLK1-5WwAEiwpm.jpg",
            "url": "https://t.co/XKCoJ2DEWn",
            "display_url": "pic.twitter.com/XKCoJ2DEWn",
            "expanded_url": "https://twitter.com/ahrest1/status/1077146411786006528/photo/1",
            "type": "photo",
            "sizes": {
              "thumb": {
                "w": 150,
                "h": 150,
                "resize": "crop"
              },
              "large": {
                "w": 2048,
                "h": 1365,
                "resize": "fit"
              },
              "small": {
                "w": 680,
                "h": 453,
                "resize": "fit"
              },
              "medium": {
                "w": 1200,
                "h": 800,
                "resize": "fit"
              }
            }
          }
        ]
      },
      "extended_entities": {
        "media": [
          {
            "id": 1077146289660411900,
            "id_str": "1077146289660411905",
            "indices": [
              63,
              86
            ],
            "media_url": "http://pbs.twimg.com/media/DvLK1-5WwAEiwpm.jpg",
            "media_url_https": "https://pbs.twimg.com/media/DvLK1-5WwAEiwpm.jpg",
            "url": "https://t.co/XKCoJ2DEWn",
            "display_url": "pic.twitter.com/XKCoJ2DEWn",
            "expanded_url": "https://twitter.com/ahrest1/status/1077146411786006528/photo/1",
            "type": "photo",
            "sizes": {
              "thumb": {
                "w": 150,
                "h": 150,
                "resize": "crop"
              },
              "large": {
                "w": 2048,
                "h": 1365,
                "resize": "fit"
              },
              "small": {
                "w": 680,
                "h": 453,
                "resize": "fit"
              },
              "medium": {
                "w": 1200,
                "h": 800,
                "resize": "fit"
              }
            }
          }
        ]
      },
      "source": "<a href=\"https://about.twitter.com/products/tweetdeck\" rel=\"nofollow\">TweetDeck</a>",
      "in_reply_to_status_id": 1077145072674721800,
      "in_reply_to_status_id_str": "1077145072674721794",
      "in_reply_to_user_id": 3955812173,
      "in_reply_to_user_id_str": "3955812173",
      "in_reply_to_screen_name": "abroadunderhood",
      "user": {
        "id": 211214492,
        "id_str": "211214492"
      },
      "geo": null,
      "coordinates": null,
      "place": null,
      "contributors": null,
      "is_quote_status": false,
      "retweet_count": 0,
      "favorite_count": 0,
      "favorited": false,
      "retweeted": false,
      "possibly_sensitive": false,
      "lang": "ru"
    },
    {
      "created_at": "Mon Dec 24 10:20:24 +0000 2018",
      "id": 1077146971046137900,
      "id_str": "1077146971046137856",
      "text": "@KabanMadan @abroadunderhood Это фактически цитата",
      "truncated": false,
      "entities": {
        "hashtags": [],
        "symbols": [],
        "user_mentions": [
          {
            "screen_name": "KabanMadan",
            "name": "Кабан Мадан",
            "id": 515277374,
            "id_str": "515277374",
            "indices": [
              0,
              11
            ]
          },
          {
            "screen_name": "abroadunderhood",
            "name": "Эброд Андерхуд",
            "id": 3955812173,
            "id_str": "3955812173",
            "indices": [
              12,
              28
            ]
          }
        ],
        "urls": []
      },
      "source": "<a href=\"http://twitter.com/download/iphone\" rel=\"nofollow\">Twitter for iPhone</a>",
      "in_reply_to_status_id": 1077146205992505300,
      "in_reply_to_status_id_str": "1077146205992505344",
      "in_reply_to_user_id": 515277374,
      "in_reply_to_user_id_str": "515277374",
      "in_reply_to_screen_name": "KabanMadan",
      "user": {
        "id": 229657175,
        "id_str": "229657175"
      },
      "geo": null,
      "coordinates": null,
      "place": null,
      "contributors": null,
      "is_quote_status": false,
      "retweet_count": 1,
      "favorite_count": 0,
      "favorited": false,
      "retweeted": false,
      "lang": "ru"
    },
    {
      "created_at": "Mon Dec 24 10:20:46 +0000 2018",
      "id": 1077147063274623000,
      "id_str": "1077147063274622977",
      "text": "@abroadunderhood Блен... Айтишнеца, уеховшая с мужем... Опяяяяяять",
      "truncated": false,
      "entities": {
        "hashtags": [],
        "symbols": [],
        "user_mentions": [
          {
            "screen_name": "abroadunderhood",
            "name": "Эброд Андерхуд",
            "id": 3955812173,
            "id_str": "3955812173",
            "indices": [
              0,
              16
            ]
          }
        ],
        "urls": []
      },
      "source": "<a href=\"http://twitter.com/download/android\" rel=\"nofollow\">Twitter for Android</a>",
      "in_reply_to_status_id": 1077144129468067800,
      "in_reply_to_status_id_str": "1077144129468067842",
      "in_reply_to_user_id": 3955812173,
      "in_reply_to_user_id_str": "3955812173",
      "in_reply_to_screen_name": "abroadunderhood",
      "user": {
        "id": 168573465,
        "id_str": "168573465"
      },
      "geo": null,
      "coordinates": null,
      "place": null,
      "contributors": null,
      "is_quote_status": false,
      "retweet_count": 0,
      "favorite_count": 3,
      "favorited": false,
      "retweeted": false,
      "lang": "ru"
    },
    {
      "created_at": "Mon Dec 24 10:21:11 +0000 2018",
      "id": 1077147164332183600,
      "id_str": "1077147164332183552",
      "text": "Короч я получила наконец-то пассворд от @abroadunderhood и теперь вы будете от меня страдать еще и там",
      "truncated": false,
      "entities": {
        "hashtags": [],
        "symbols": [],
        "user_mentions": [
          {
            "screen_name": "abroadunderhood",
            "name": "Эброд Андерхуд",
            "id": 3955812173,
            "id_str": "3955812173",
            "indices": [
              40,
              56
            ]
          }
        ],
        "urls": []
      },
      "source": "<a href=\"http://twitter.com/download/iphone\" rel=\"nofollow\">Twitter for iPhone</a>",
      "in_reply_to_status_id": null,
      "in_reply_to_status_id_str": null,
      "in_reply_to_user_id": null,
      "in_reply_to_user_id_str": null,
      "in_reply_to_screen_name": null,
      "user": {
        "id": 229657175,
        "id_str": "229657175"
      },
      "geo": null,
      "coordinates": null,
      "place": null,
      "contributors": null,
      "is_quote_status": false,
      "retweet_count": 0,
      "favorite_count": 2,
      "favorited": false,
      "retweeted": false,
      "lang": "ru"
    },
    {
      "created_at": "Mon Dec 24 10:22:54 +0000 2018",
      "id": 1077147598715322400,
      "id_str": "1077147598715322368",
      "text": "@abroadunderhood https://t.co/6fosGzJaUt",
      "truncated": false,
      "entities": {
        "hashtags": [],
        "symbols": [],
        "user_mentions": [
          {
            "screen_name": "abroadunderhood",
            "name": "Эброд Андерхуд",
            "id": 3955812173,
            "id_str": "3955812173",
            "indices": [
              0,
              16
            ]
          }
        ],
        "urls": [],
        "media": [
          {
            "id": 1077147578800709600,
            "id_str": "1077147578800709632",
            "indices": [
              17,
              40
            ],
            "media_url": "http://pbs.twimg.com/media/DvLMBBUWoAAve9T.jpg",
            "media_url_https": "https://pbs.twimg.com/media/DvLMBBUWoAAve9T.jpg",
            "url": "https://t.co/6fosGzJaUt",
            "display_url": "pic.twitter.com/6fosGzJaUt",
            "expanded_url": "https://twitter.com/ELukyanov/status/1077147598715322368/photo/1",
            "type": "photo",
            "sizes": {
              "thumb": {
                "w": 150,
                "h": 150,
                "resize": "crop"
              },
              "small": {
                "w": 492,
                "h": 680,
                "resize": "fit"
              },
              "medium": {
                "w": 867,
                "h": 1200,
                "resize": "fit"
              },
              "large": {
                "w": 1012,
                "h": 1400,
                "resize": "fit"
              }
            }
          }
        ]
      },
      "extended_entities": {
        "media": [
          {
            "id": 1077147578800709600,
            "id_str": "1077147578800709632",
            "indices": [
              17,
              40
            ],
            "media_url": "http://pbs.twimg.com/media/DvLMBBUWoAAve9T.jpg",
            "media_url_https": "https://pbs.twimg.com/media/DvLMBBUWoAAve9T.jpg",
            "url": "https://t.co/6fosGzJaUt",
            "display_url": "pic.twitter.com/6fosGzJaUt",
            "expanded_url": "https://twitter.com/ELukyanov/status/1077147598715322368/photo/1",
            "type": "photo",
            "sizes": {
              "thumb": {
                "w": 150,
                "h": 150,
                "resize": "crop"
              },
              "small": {
                "w": 492,
                "h": 680,
                "resize": "fit"
              },
              "medium": {
                "w": 867,
                "h": 1200,
                "resize": "fit"
              },
              "large": {
                "w": 1012,
                "h": 1400,
                "resize": "fit"
              }
            }
          },
          {
            "id": 1077147583838150700,
            "id_str": "1077147583838150656",
            "indices": [
              17,
              40
            ],
            "media_url": "http://pbs.twimg.com/media/DvLMBUFX4AAcb-f.jpg",
            "media_url_https": "https://pbs.twimg.com/media/DvLMBUFX4AAcb-f.jpg",
            "url": "https://t.co/6fosGzJaUt",
            "display_url": "pic.twitter.com/6fosGzJaUt",
            "expanded_url": "https://twitter.com/ELukyanov/status/1077147598715322368/photo/1",
            "type": "photo",
            "sizes": {
              "large": {
                "w": 1142,
                "h": 1400,
                "resize": "fit"
              },
              "thumb": {
                "w": 150,
                "h": 150,
                "resize": "crop"
              },
              "small": {
                "w": 555,
                "h": 680,
                "resize": "fit"
              },
              "medium": {
                "w": 979,
                "h": 1200,
                "resize": "fit"
              }
            }
          },
          {
            "id": 1077147589202624500,
            "id_str": "1077147589202624513",
            "indices": [
              17,
              40
            ],
            "media_url": "http://pbs.twimg.com/media/DvLMBoEXQAEkcos.jpg",
            "media_url_https": "https://pbs.twimg.com/media/DvLMBoEXQAEkcos.jpg",
            "url": "https://t.co/6fosGzJaUt",
            "display_url": "pic.twitter.com/6fosGzJaUt",
            "expanded_url": "https://twitter.com/ELukyanov/status/1077147598715322368/photo/1",
            "type": "photo",
            "sizes": {
              "thumb": {
                "w": 150,
                "h": 150,
                "resize": "crop"
              },
              "large": {
                "w": 1017,
                "h": 1400,
                "resize": "fit"
              },
              "medium": {
                "w": 872,
                "h": 1200,
                "resize": "fit"
              },
              "small": {
                "w": 494,
                "h": 680,
                "resize": "fit"
              }
            }
          },
          {
            "id": 1077147594680422400,
            "id_str": "1077147594680422401",
            "indices": [
              17,
              40
            ],
            "media_url": "http://pbs.twimg.com/media/DvLMB8eX0AEjVuA.jpg",
            "media_url_https": "https://pbs.twimg.com/media/DvLMB8eX0AEjVuA.jpg",
            "url": "https://t.co/6fosGzJaUt",
            "display_url": "pic.twitter.com/6fosGzJaUt",
            "expanded_url": "https://twitter.com/ELukyanov/status/1077147598715322368/photo/1",
            "type": "photo",
            "sizes": {
              "thumb": {
                "w": 150,
                "h": 150,
                "resize": "crop"
              },
              "small": {
                "w": 492,
                "h": 680,
                "resize": "fit"
              },
              "large": {
                "w": 1013,
                "h": 1400,
                "resize": "fit"
              },
              "medium": {
                "w": 868,
                "h": 1200,
                "resize": "fit"
              }
            }
          }
        ]
      },
      "source": "<a href=\"http://mvilla.it/fenix\" rel=\"nofollow\">Fenix 2</a>",
      "in_reply_to_status_id": 1077145072674721800,
      "in_reply_to_status_id_str": "1077145072674721794",
      "in_reply_to_user_id": 3955812173,
      "in_reply_to_user_id_str": "3955812173",
      "in_reply_to_screen_name": "abroadunderhood",
      "user": {
        "id": 169993781,
        "id_str": "169993781"
      },
      "geo": null,
      "coordinates": null,
      "place": null,
      "contributors": null,
      "is_quote_status": false,
      "retweet_count": 0,
      "favorite_count": 0,
      "favorited": false,
      "retweeted": false,
      "possibly_sensitive": false,
      "lang": "und"
    },
    {
      "created_at": "Mon Dec 24 10:27:37 +0000 2018",
      "id": 1077148784646414300,
      "id_str": "1077148784646414336",
      "text": "@olgazju @abroadunderhood Огоооооооо",
      "truncated": false,
      "entities": {
        "hashtags": [],
        "symbols": [],
        "user_mentions": [
          {
            "screen_name": "olgazju",
            "name": "OlgaZju",
            "id": 229657175,
            "id_str": "229657175",
            "indices": [
              0,
              8
            ]
          },
          {
            "screen_name": "abroadunderhood",
            "name": "Эброд Андерхуд",
            "id": 3955812173,
            "id_str": "3955812173",
            "indices": [
              9,
              25
            ]
          }
        ],
        "urls": []
      },
      "source": "<a href=\"http://twitter.com/download/android\" rel=\"nofollow\">Twitter for Android</a>",
      "in_reply_to_status_id": 1077147164332183600,
      "in_reply_to_status_id_str": "1077147164332183552",
      "in_reply_to_user_id": 229657175,
      "in_reply_to_user_id_str": "229657175",
      "in_reply_to_screen_name": "olgazju",
      "user": {
        "id": 328706345,
        "id_str": "328706345"
      },
      "geo": null,
      "coordinates": null,
      "place": null,
      "contributors": null,
      "is_quote_status": false,
      "retweet_count": 0,
      "favorite_count": 0,
      "favorited": false,
      "retweeted": false,
      "lang": "ru"
    },
    {
      "created_at": "Mon Dec 24 10:28:41 +0000 2018",
      "id": 1077149054403076100,
      "id_str": "1077149054403076097",
      "text": "@abroadunderhood вот дед твой еврей, поэтому вот тебе паспорт и плюшечки от Израиля, как репатрианту. - true story",
      "truncated": false,
      "entities": {
        "hashtags": [],
        "symbols": [],
        "user_mentions": [
          {
            "screen_name": "abroadunderhood",
            "name": "Эброд Андерхуд",
            "id": 3955812173,
            "id_str": "3955812173",
            "indices": [
              0,
              16
            ]
          }
        ],
        "urls": []
      },
      "source": "<a href=\"http://twitter.com\" rel=\"nofollow\">Twitter Web Client</a>",
      "in_reply_to_status_id": 1077144129468067800,
      "in_reply_to_status_id_str": "1077144129468067842",
      "in_reply_to_user_id": 3955812173,
      "in_reply_to_user_id_str": "3955812173",
      "in_reply_to_screen_name": "abroadunderhood",
      "user": {
        "id": 463761977,
        "id_str": "463761977"
      },
      "geo": null,
      "coordinates": null,
      "place": null,
      "contributors": null,
      "is_quote_status": false,
      "retweet_count": 0,
      "favorite_count": 0,
      "favorited": false,
      "retweeted": false,
      "lang": "ru"
    },
    {
      "created_at": "Mon Dec 24 10:31:32 +0000 2018",
      "id": 1077149770857234400,
      "id_str": "1077149770857234432",
      "text": "@abroadunderhood @olgazju Оооооо! Здравствуйте! Очень давно ждала...",
      "truncated": false,
      "entities": {
        "hashtags": [],
        "symbols": [],
        "user_mentions": [
          {
            "screen_name": "abroadunderhood",
            "name": "Эброд Андерхуд",
            "id": 3955812173,
            "id_str": "3955812173",
            "indices": [
              0,
              16
            ]
          },
          {
            "screen_name": "olgazju",
            "name": "OlgaZju",
            "id": 229657175,
            "id_str": "229657175",
            "indices": [
              17,
              25
            ]
          }
        ],
        "urls": []
      },
      "source": "<a href=\"http://twitter.com/download/android\" rel=\"nofollow\">Twitter for Android</a>",
      "in_reply_to_status_id": 1077143921321525200,
      "in_reply_to_status_id_str": "1077143921321525249",
      "in_reply_to_user_id": 3955812173,
      "in_reply_to_user_id_str": "3955812173",
      "in_reply_to_screen_name": "abroadunderhood",
      "user": {
        "id": 104126792,
        "id_str": "104126792"
      },
      "geo": null,
      "coordinates": null,
      "place": null,
      "contributors": null,
      "is_quote_status": false,
      "retweet_count": 0,
      "favorite_count": 0,
      "favorited": false,
      "retweeted": false,
      "lang": "ru"
    },
    {
      "created_at": "Mon Dec 24 10:31:41 +0000 2018",
      "id": 1077149810547925000,
      "id_str": "1077149810547924992",
      "text": "@ELukyanov @abroadunderhood @olgazju Guten Tag.",
      "truncated": false,
      "entities": {
        "hashtags": [],
        "symbols": [],
        "user_mentions": [
          {
            "screen_name": "ELukyanov",
            "name": "Лукьянов Евгений А.",
            "id": 169993781,
            "id_str": "169993781",
            "indices": [
              0,
              10
            ]
          },
          {
            "screen_name": "abroadunderhood",
            "name": "Эброд Андерхуд",
            "id": 3955812173,
            "id_str": "3955812173",
            "indices": [
              11,
              27
            ]
          },
          {
            "screen_name": "olgazju",
            "name": "OlgaZju",
            "id": 229657175,
            "id_str": "229657175",
            "indices": [
              28,
              36
            ]
          }
        ],
        "urls": []
      },
      "source": "<a href=\"http://twitter.com/download/android\" rel=\"nofollow\">Twitter for Android</a>",
      "in_reply_to_status_id": 1077145098532606000,
      "in_reply_to_status_id_str": "1077145098532605957",
      "in_reply_to_user_id": 169993781,
      "in_reply_to_user_id_str": "169993781",
      "in_reply_to_screen_name": "ELukyanov",
      "user": {
        "id": 86304279,
        "id_str": "86304279"
      },
      "geo": null,
      "coordinates": null,
      "place": null,
      "contributors": null,
      "is_quote_status": false,
      "retweet_count": 0,
      "favorite_count": 0,
      "favorited": false,
      "retweeted": false,
      "lang": "de"
    },
    {
      "created_at": "Mon Dec 24 10:32:14 +0000 2018",
      "id": 1077149948532191200,
      "id_str": "1077149948532191232",
      "text": "@abroadunderhood @olgazju Очень приятно!",
      "truncated": false,
      "entities": {
        "hashtags": [],
        "symbols": [],
        "user_mentions": [
          {
            "screen_name": "abroadunderhood",
            "name": "Эброд Андерхуд",
            "id": 3955812173,
            "id_str": "3955812173",
            "indices": [
              0,
              16
            ]
          },
          {
            "screen_name": "olgazju",
            "name": "OlgaZju",
            "id": 229657175,
            "id_str": "229657175",
            "indices": [
              17,
              25
            ]
          }
        ],
        "urls": []
      },
      "source": "<a href=\"http://twitter.com\" rel=\"nofollow\">Twitter Web Client</a>",
      "in_reply_to_status_id": 1077143921321525200,
      "in_reply_to_status_id_str": "1077143921321525249",
      "in_reply_to_user_id": 3955812173,
      "in_reply_to_user_id_str": "3955812173",
      "in_reply_to_screen_name": "abroadunderhood",
      "user": {
        "id": 1890458946,
        "id_str": "1890458946"
      },
      "geo": null,
      "coordinates": null,
      "place": null,
      "contributors": null,
      "is_quote_status": false,
      "retweet_count": 0,
      "favorite_count": 1,
      "favorited": true,
      "retweeted": false,
      "lang": "ru"
    },
    {
      "created_at": "Mon Dec 24 10:36:59 +0000 2018",
      "id": 1077151140784033800,
      "id_str": "1077151140784033792",
      "text": "@abroadunderhood Можно того из Германии ещё на недельку?",
      "truncated": false,
      "entities": {
        "hashtags": [],
        "symbols": [],
        "user_mentions": [
          {
            "screen_name": "abroadunderhood",
            "name": "Эброд Андерхуд",
            "id": 3955812173,
            "id_str": "3955812173",
            "indices": [
              0,
              16
            ]
          }
        ],
        "urls": []
      },
      "source": "<a href=\"http://twitter.com/download/iphone\" rel=\"nofollow\">Twitter for iPhone</a>",
      "in_reply_to_status_id": 1077144129468067800,
      "in_reply_to_status_id_str": "1077144129468067842",
      "in_reply_to_user_id": 3955812173,
      "in_reply_to_user_id_str": "3955812173",
      "in_reply_to_screen_name": "abroadunderhood",
      "user": {
        "id": 2230347070,
        "id_str": "2230347070"
      },
      "geo": null,
      "coordinates": null,
      "place": null,
      "contributors": null,
      "is_quote_status": false,
      "retweet_count": 0,
      "favorite_count": 0,
      "favorited": false,
      "retweeted": false,
      "lang": "ru"
    },
    {
      "created_at": "Mon Dec 24 10:40:34 +0000 2018",
      "id": 1077152044060938200,
      "id_str": "1077152044060938240",
      "text": "Посмотрим кто задаст острые вопросы о том где чьё текущему @abroadunderhood 🙂",
      "truncated": false,
      "entities": {
        "hashtags": [],
        "symbols": [],
        "user_mentions": [
          {
            "screen_name": "abroadunderhood",
            "name": "Эброд Андерхуд",
            "id": 3955812173,
            "id_str": "3955812173",
            "indices": [
              59,
              75
            ]
          }
        ],
        "urls": []
      },
      "source": "<a href=\"http://www.samruston.co.uk\" rel=\"nofollow\">Flamingo for Android</a>",
      "in_reply_to_status_id": null,
      "in_reply_to_status_id_str": null,
      "in_reply_to_user_id": null,
      "in_reply_to_user_id_str": null,
      "in_reply_to_screen_name": null,
      "user": {
        "id": 13020892,
        "id_str": "13020892"
      },
      "geo": null,
      "coordinates": null,
      "place": null,
      "contributors": null,
      "is_quote_status": false,
      "retweet_count": 0,
      "favorite_count": 0,
      "favorited": false,
      "retweeted": false,
      "lang": "ru"
    },
    {
      "created_at": "Mon Dec 24 10:41:24 +0000 2018",
      "id": 1077152253927133200,
      "id_str": "1077152253927133184",
      "text": "@abroadunderhood Однако вопрос сразу с места - насколько нужен иврит для работы в АйТи? А то как раз айтишник, план… https://t.co/LJcAbJXH7t",
      "truncated": true,
      "entities": {
        "hashtags": [],
        "symbols": [],
        "user_mentions": [
          {
            "screen_name": "abroadunderhood",
            "name": "Эброд Андерхуд",
            "id": 3955812173,
            "id_str": "3955812173",
            "indices": [
              0,
              16
            ]
          }
        ],
        "urls": [
          {
            "url": "https://t.co/LJcAbJXH7t",
            "expanded_url": "https://twitter.com/i/web/status/1077152253927133184",
            "display_url": "twitter.com/i/web/status/1…",
            "indices": [
              117,
              140
            ]
          }
        ]
      },
      "source": "<a href=\"http://twitter.com\" rel=\"nofollow\">Twitter Web Client</a>",
      "in_reply_to_status_id": 1077144409056165900,
      "in_reply_to_status_id_str": "1077144409056165888",
      "in_reply_to_user_id": 3955812173,
      "in_reply_to_user_id_str": "3955812173",
      "in_reply_to_screen_name": "abroadunderhood",
      "user": {
        "id": 74373151,
        "id_str": "74373151"
      },
      "geo": null,
      "coordinates": null,
      "place": null,
      "contributors": null,
      "is_quote_status": false,
      "retweet_count": 0,
      "favorite_count": 0,
      "favorited": false,
      "retweeted": false,
      "lang": "ru"
    },
    {
      "created_at": "Mon Dec 24 10:41:53 +0000 2018",
      "id": 1077152377050808300,
      "id_str": "1077152377050808321",
      "text": "@abroadunderhood Про Израиль совсем не интересно, там все не несколько порядков проще чем в Сингапуре. Отписываюсь",
      "truncated": false,
      "entities": {
        "hashtags": [],
        "symbols": [],
        "user_mentions": [
          {
            "screen_name": "abroadunderhood",
            "name": "Эброд Андерхуд",
            "id": 3955812173,
            "id_str": "3955812173",
            "indices": [
              0,
              16
            ]
          }
        ],
        "urls": []
      },
      "source": "<a href=\"http://twitter.com\" rel=\"nofollow\">Twitter Web Client</a>",
      "in_reply_to_status_id": 1077152113359237100,
      "in_reply_to_status_id_str": "1077152113359237120",
      "in_reply_to_user_id": 3955812173,
      "in_reply_to_user_id_str": "3955812173",
      "in_reply_to_screen_name": "abroadunderhood",
      "user": {
        "id": 2554906118,
        "id_str": "2554906118"
      },
      "geo": null,
      "coordinates": null,
      "place": null,
      "contributors": null,
      "is_quote_status": false,
      "retweet_count": 0,
      "favorite_count": 0,
      "favorited": false,
      "retweeted": false,
      "lang": "ru"
    },
    {
      "created_at": "Mon Dec 24 10:42:00 +0000 2018",
      "id": 1077152404477493200,
      "id_str": "1077152404477493248",
      "text": "@abroadunderhood Один вопрос, вы из Одессы?",
      "truncated": false,
      "entities": {
        "hashtags": [],
        "symbols": [],
        "user_mentions": [
          {
            "screen_name": "abroadunderhood",
            "name": "Эброд Андерхуд",
            "id": 3955812173,
            "id_str": "3955812173",
            "indices": [
              0,
              16
            ]
          }
        ],
        "urls": []
      },
      "source": "<a href=\"http://twitter.com/download/iphone\" rel=\"nofollow\">Twitter for iPhone</a>",
      "in_reply_to_status_id": 1077152113359237100,
      "in_reply_to_status_id_str": "1077152113359237120",
      "in_reply_to_user_id": 3955812173,
      "in_reply_to_user_id_str": "3955812173",
      "in_reply_to_screen_name": "abroadunderhood",
      "user": {
        "id": 964643816165789700,
        "id_str": "964643816165789696"
      },
      "geo": null,
      "coordinates": null,
      "place": null,
      "contributors": null,
      "is_quote_status": false,
      "retweet_count": 0,
      "favorite_count": 0,
      "favorited": false,
      "retweeted": false,
      "lang": "ru"
    },
    {
      "created_at": "Mon Dec 24 10:42:21 +0000 2018",
      "id": 1077152494969593900,
      "id_str": "1077152494969593856",
      "text": "@abroadunderhood @olgazju Про Израиль неинтересно :( к сожалению",
      "truncated": false,
      "entities": {
        "hashtags": [],
        "symbols": [],
        "user_mentions": [
          {
            "screen_name": "abroadunderhood",
            "name": "Эброд Андерхуд",
            "id": 3955812173,
            "id_str": "3955812173",
            "indices": [
              0,
              16
            ]
          },
          {
            "screen_name": "olgazju",
            "name": "OlgaZju",
            "id": 229657175,
            "id_str": "229657175",
            "indices": [
              17,
              25
            ]
          }
        ],
        "urls": []
      },
      "source": "<a href=\"http://twitter.com/download/iphone\" rel=\"nofollow\">Twitter for iPhone</a>",
      "in_reply_to_status_id": 1077143921321525200,
      "in_reply_to_status_id_str": "1077143921321525249",
      "in_reply_to_user_id": 3955812173,
      "in_reply_to_user_id_str": "3955812173",
      "in_reply_to_screen_name": "abroadunderhood",
      "user": {
        "id": 446004388,
        "id_str": "446004388"
      },
      "geo": null,
      "coordinates": null,
      "place": null,
      "contributors": null,
      "is_quote_status": false,
      "retweet_count": 0,
      "favorite_count": 0,
      "favorited": false,
      "retweeted": false,
      "lang": "ru"
    },
    {
      "created_at": "Mon Dec 24 10:42:23 +0000 2018",
      "id": 1077152499608506400,
      "id_str": "1077152499608506369",
      "text": "@abroadunderhood муж.",
      "truncated": false,
      "entities": {
        "hashtags": [],
        "symbols": [],
        "user_mentions": [
          {
            "screen_name": "abroadunderhood",
            "name": "Эброд Андерхуд",
            "id": 3955812173,
            "id_str": "3955812173",
            "indices": [
              0,
              16
            ]
          }
        ],
        "urls": []
      },
      "source": "<a href=\"https://about.twitter.com/products/tweetdeck\" rel=\"nofollow\">TweetDeck</a>",
      "in_reply_to_status_id": 1077152384151941100,
      "in_reply_to_status_id_str": "1077152384151941121",
      "in_reply_to_user_id": 3955812173,
      "in_reply_to_user_id_str": "3955812173",
      "in_reply_to_screen_name": "abroadunderhood",
      "user": {
        "id": 119823449,
        "id_str": "119823449"
      },
      "geo": null,
      "coordinates": null,
      "place": null,
      "contributors": null,
      "is_quote_status": false,
      "retweet_count": 0,
      "favorite_count": 0,
      "favorited": false,
      "retweeted": false,
      "lang": "ru"
    },
    {
      "created_at": "Mon Dec 24 10:42:36 +0000 2018",
      "id": 1077152554268745700,
      "id_str": "1077152554268745729",
      "text": "@abroadunderhood Муж хоть еврей?!",
      "truncated": false,
      "entities": {
        "hashtags": [],
        "symbols": [],
        "user_mentions": [
          {
            "screen_name": "abroadunderhood",
            "name": "Эброд Андерхуд",
            "id": 3955812173,
            "id_str": "3955812173",
            "indices": [
              0,
              16
            ]
          }
        ],
        "urls": []
      },
      "source": "<a href=\"http://twitter.com/download/android\" rel=\"nofollow\">Twitter for Android</a>",
      "in_reply_to_status_id": 1077152384151941100,
      "in_reply_to_status_id_str": "1077152384151941121",
      "in_reply_to_user_id": 3955812173,
      "in_reply_to_user_id_str": "3955812173",
      "in_reply_to_screen_name": "abroadunderhood",
      "user": {
        "id": 10533432,
        "id_str": "10533432"
      },
      "geo": null,
      "coordinates": null,
      "place": null,
      "contributors": null,
      "is_quote_status": false,
      "retweet_count": 0,
      "favorite_count": 0,
      "favorited": false,
      "retweeted": false,
      "lang": "ru"
    },
    {
      "created_at": "Mon Dec 24 10:43:03 +0000 2018",
      "id": 1077152667816869900,
      "id_str": "1077152667816869888",
      "text": "@abroadunderhood А про хатуль мадан расскажешь нам?;)",
      "truncated": false,
      "entities": {
        "hashtags": [],
        "symbols": [],
        "user_mentions": [
          {
            "screen_name": "abroadunderhood",
            "name": "Эброд Андерхуд",
            "id": 3955812173,
            "id_str": "3955812173",
            "indices": [
              0,
              16
            ]
          }
        ],
        "urls": []
      },
      "source": "<a href=\"http://tapbots.com/tweetbot\" rel=\"nofollow\">Tweetbot for iΟS</a>",
      "in_reply_to_status_id": 1077152113359237100,
      "in_reply_to_status_id_str": "1077152113359237120",
      "in_reply_to_user_id": 3955812173,
      "in_reply_to_user_id_str": "3955812173",
      "in_reply_to_screen_name": "abroadunderhood",
      "user": {
        "id": 22441561,
        "id_str": "22441561"
      },
      "geo": null,
      "coordinates": null,
      "place": {
        "id": "ed484e8043005985",
        "url": "https://api.twitter.com/1.1/geo/id/ed484e8043005985.json",
        "place_type": "city",
        "name": "Красное Село",
        "full_name": "Красное Село, Россия",
        "country_code": "RU",
        "country": "Russia",
        "contained_within": [],
        "bounding_box": {
          "type": "Polygon",
          "coordinates": [
            [
              [
                30.0347284,
                59.6918497
              ],
              [
                30.1601297,
                59.6918497
              ],
              [
                30.1601297,
                59.8090168
              ],
              [
                30.0347284,
                59.8090168
              ]
            ]
          ]
        },
        "attributes": {}
      },
      "contributors": null,
      "is_quote_status": false,
      "retweet_count": 0,
      "favorite_count": 0,
      "favorited": false,
      "retweeted": false,
      "lang": "ru"
    },
    {
      "created_at": "Mon Dec 24 10:43:11 +0000 2018",
      "id": 1077152703787221000,
      "id_str": "1077152703787220992",
      "text": "@abroadunderhood войнушечка с арабами. Автор гендерка что-ли?",
      "truncated": false,
      "entities": {
        "hashtags": [],
        "symbols": [],
        "user_mentions": [
          {
            "screen_name": "abroadunderhood",
            "name": "Эброд Андерхуд",
            "id": 3955812173,
            "id_str": "3955812173",
            "indices": [
              0,
              16
            ]
          }
        ],
        "urls": []
      },
      "source": "<a href=\"http://twitter.com\" rel=\"nofollow\">Twitter Web Client</a>",
      "in_reply_to_status_id": 1077152113359237100,
      "in_reply_to_status_id_str": "1077152113359237120",
      "in_reply_to_user_id": 3955812173,
      "in_reply_to_user_id_str": "3955812173",
      "in_reply_to_screen_name": "abroadunderhood",
      "user": {
        "id": 463761977,
        "id_str": "463761977"
      },
      "geo": null,
      "coordinates": null,
      "place": null,
      "contributors": null,
      "is_quote_status": false,
      "retweet_count": 0,
      "favorite_count": 0,
      "favorited": false,
      "retweeted": false,
      "lang": "ru"
    }
  ]
}
